thermosteam/__init__.py
thermosteam/_chemical.py
thermosteam/_chemical_data.py
thermosteam/_chemicals.py
thermosteam/_multi_stream.py
thermosteam/_phase.py
thermosteam/_settings.py
thermosteam/_stream.py
thermosteam/_thermal_condition.py
thermosteam/_thermo.py
thermosteam/_thermo_data.py
thermosteam/constants.py
thermosteam/exceptions.py
thermosteam/free_energy.py
thermosteam/functional.py
thermosteam/functors.py
thermosteam/indexer.py
thermosteam/separations.py
thermosteam/units_of_measure.py
thermosteam/units_of_measure.txt
thermosteam/base/__init__.py
thermosteam/base/documenter.py
thermosteam/base/functor.py
thermosteam/base/phase_handle.py
thermosteam/chemicals/__init__.py
thermosteam/chemicals/elements.py
thermosteam/chemicals/identifiers.py
thermosteam/chemicals/reaction.py
thermosteam/chemicals/Reaction/Biochemicals Hf.tsv
thermosteam/equilibrium/__init__.py
thermosteam/equilibrium/activity_coefficients.py
thermosteam/equilibrium/binary_phase_fraction.py
thermosteam/equilibrium/bubble_point.py
thermosteam/equilibrium/dew_point.py
thermosteam/equilibrium/domain.py
thermosteam/equilibrium/equilibrium.py
thermosteam/equilibrium/flash_package.py
thermosteam/equilibrium/fugacities.py
thermosteam/equilibrium/fugacity_coefficients.py
thermosteam/equilibrium/ideal.py
thermosteam/equilibrium/lle.py
thermosteam/equilibrium/plot_equilibrium.py
thermosteam/equilibrium/poyinting_correction_factors.py
thermosteam/equilibrium/sle.py
thermosteam/equilibrium/unifac.py
thermosteam/equilibrium/vle.py
thermosteam/equilibrium/UNIFAC/DDBST UNIFAC-Dortmund assignments.json
thermosteam/equilibrium/UNIFAC/DDBST UNIFAC-PSRK assignments.json
thermosteam/equilibrium/UNIFAC/DDBST UNIFAC-original assignments.json
thermosteam/equilibrium/UNIFAC/PSRK interaction parameters.json
thermosteam/equilibrium/UNIFAC/UNIFAC modified Dortmund interaction parameters.json
thermosteam/equilibrium/UNIFAC/UNIFAC modified NIST 2015 interaction parameters.json
thermosteam-0.29.3.dist-info/AUTHORS.rst
thermosteam-0.29.3.dist-info/LICENSE.txt
thermosteam-0.29.3.dist-info/METADATA
thermosteam-0.29.3.dist-info/WHEEL
thermosteam-0.29.3.dist-info/top_level.txt
thermosteam-0.29.3.dist-info/RECORD
