Metadata-Version: 2.1
Name: thermosteam
Version: 0.29.3
Summary: BioSTEAM's Premier Thermodynamic Engine
Home-page: https://github.com/BioSTEAMDevelopmentGroup/thermosteam
Download-URL: https://github.com/BioSTEAMDevelopmentGroup/thermosteam.git
Author: Yoel Cortes-Pena
Author-email: yoelcortes@gmail.com
License: MIT
Keywords: thermodynamics,chemical engineering,mass and energy balance,material properties,phase equilibrium
Platform: Windows
Platform: Mac
Platform: Linux
Classifier: Development Status :: 3 - Alpha
Classifier: Environment :: Console
Classifier: License :: OSI Approved :: University of Illinois/NCSA Open Source License
Classifier: License :: OSI Approved :: MIT License
Classifier: Topic :: Scientific/Engineering
Classifier: Topic :: Scientific/Engineering :: Chemistry
Classifier: Topic :: Scientific/Engineering :: Mathematics
Classifier: Intended Audience :: Developers
Classifier: Intended Audience :: Education
Classifier: Intended Audience :: Manufacturing
Classifier: Intended Audience :: Science/Research
Classifier: Natural Language :: English
Classifier: Operating System :: MacOS
Classifier: Operating System :: Microsoft :: Windows
Classifier: Operating System :: POSIX
Classifier: Operating System :: POSIX :: BSD
Classifier: Operating System :: POSIX :: Linux
Classifier: Operating System :: Unix
Classifier: Programming Language :: Python :: 3.8
Classifier: Programming Language :: Python :: 3.9
Classifier: Programming Language :: Python :: 3.10
Classifier: Programming Language :: Python :: Implementation :: CPython
Classifier: Topic :: Education
Requires-Python: >=3.8
License-File: LICENSE.txt
License-File: AUTHORS.rst
Requires-Dist: numpy (>=1.22)
Requires-Dist: pint (>=0.9)
Requires-Dist: scipy (>=1.5)
Requires-Dist: thermo (>=0.2.9)
Requires-Dist: IPython (>=7.9.0)
Requires-Dist: colorpalette (>=0.3.3)
Requires-Dist: pandas (>=0.25.2)
Requires-Dist: matplotlib (>=3.1.1)
Requires-Dist: xlrd (>=1.2.0)
Requires-Dist: openpyxl (>=3.0.0)
Requires-Dist: free-properties (>=0.3.6)
Requires-Dist: flexsolve (>=0.5.4)
Requires-Dist: numba (>=0.56.0)
Requires-Dist: pyglet
Provides-Extra: dev
Requires-Dist: biorefineries (>=2.23.16) ; extra == 'dev'
Requires-Dist: sympy ; extra == 'dev'
Requires-Dist: sphinx ; extra == 'dev'
Requires-Dist: sphinx-rtd-theme ; extra == 'dev'
Requires-Dist: pyyaml ; extra == 'dev'
Requires-Dist: pytest-cov ; extra == 'dev'
Requires-Dist: coveralls ; extra == 'dev'
